pdm_pyfuture-0.1.13.dist-info/METADATA
pdm_pyfuture-0.1.13.dist-info/WHEEL
pdm_pyfuture-0.1.13.dist-info/entry_points.txt
pdm_pyfuture/__init__.py
pdm_pyfuture/__main__.py
pdm_pyfuture/build.py
pdm_pyfuture-0.1.13.dist-info/RECORD
