Metadata-Version: 2.1
Name: pdm-pyfuture
Version: 0.1.13
Author-Email: Zhan Rongrui <2742392377@qq.com>
License: MIT
Project-URL: Homepage, https://github.com/zrr1999/pdm-pyfuture.git
Project-URL: Repository, https://github.com/zrr1999/pdm-pyfuture.git
Requires-Python: >=3.9
Requires-Dist: pyfuture
Requires-Dist: loguru
